gdplot/__init__.py
gdriveplot/__init__.py
gdriveplotter/__init__.py
gdriveplotter-0.2.dist-info/METADATA
gdriveplotter-0.2.dist-info/WHEEL
gdriveplotter-0.2.dist-info/top_level.txt
gdriveplotter-0.2.dist-info/RECORD
