Metadata-Version: 2.1
Name: gdriveplotter
Version: 0.2
Summary: Reads Gsheets from Gdrive and Plots graph
Home-page: UNKNOWN
Author: Akshay Mohite
License: UNKNOWN
Platform: UNKNOWN
Requires-Dist: pandas
Requires-Dist: matplotlib
Requires-Dist: gspread
